call_flow/__init__.py
call_flow/tools/__init__.py
call_flow/tools/call_flow_tool.py
call_flow/tools/utils.py
call_flow/yamls/call_flow_tool.yaml
tests/__init__.py
tests/test_call_flow_tool.py
plIntelligence_flow-0.0.1.dist-info/METADATA
plIntelligence_flow-0.0.1.dist-info/WHEEL
plIntelligence_flow-0.0.1.dist-info/entry_points.txt
plIntelligence_flow-0.0.1.dist-info/top_level.txt
plIntelligence_flow-0.0.1.dist-info/RECORD
