Metadata-Version: 2.1
Name: plIntelligence_flow
Version: 0.0.1
Summary: Import another flow in prompt flow
